MANIFEST.in
README.md
setup.py
./variables
pyshipper/__init__.py
pyshipper/__main__.py
pyshipper.egg-info/PKG-INFO
pyshipper.egg-info/SOURCES.txt
pyshipper.egg-info/dependency_links.txt
pyshipper.egg-info/top_level.txt
pyshipper/main/__init__.py
pyshipper/main/myclass.py
pyshipper/main/parser.py