Metadata-Version: 2.1
Name: pyshipper
Version: 0.0.4
Summary: demo boilercode
Home-page: https://github.com/LINKIT-Group/pyshipper
Author: Anthony Potappel
Author-email: anthony.potappel@gmail.com
License: UNKNOWN
Platform: UNKNOWN
Classifier: Operating System :: POSIX :: Linux
Classifier: License :: OSI Approved :: MIT License
Classifier: Programming Language :: Python :: 3.5
Classifier: Programming Language :: Python :: 3.6
Classifier: Programming Language :: Python :: 3.7
